[
  {
    "visitorInfo" : {
      "imageName" : "",
      "message" : "关注一些人，回这里看看有什么惊喜"
    },
    "className" : "HQAViewController",
    "title" : "首页",
    "imageName" : "a"
  },
  {
    "visitorInfo" : {
      "imageName" : "visitordiscover_image_message",
      "message" : "登录后，别人评论你的微博，发给你的信息，都会在这里收到通知"
    },
    "className" : "HQBViewController",
    "title" : "消息",
    "imageName" : "b"
  },
  {
    "className" : "UIViewController"
  },
  {
    "visitorInfo" : {
      "imageName" : "visitordiscover_image_message",
      "message" : "登录后，最新、最热微博尽在掌握，不再会与时事潮流擦肩而过"
    },
    "className" : "HQCViewController",
    "title" : "发现",
    "imageName" : "c"
  },
  {
    "visitorInfo" : {
      "imageName" : "visitordiscover_image_profile",
      "message" : "登录后，你的微博、相册，个人资料会显示在这里，显示给别人"
    },
    "className" : "HQDViewController",
    "title" : "我",
    "imageName" : "d"
  }
]
